star_ray_pygame/__init__.py
star_ray_pygame/actuator.py
star_ray_pygame/ambient.py
star_ray_pygame/avatar.py
star_ray_pygame/cairosurface.py
star_ray_pygame/event.py
star_ray_pygame/utils.py
star_ray_pygame/view.py
star_ray_pygame-0.0.11.dist-info/LICENSE
star_ray_pygame-0.0.11.dist-info/METADATA
star_ray_pygame-0.0.11.dist-info/WHEEL
star_ray_pygame-0.0.11.dist-info/top_level.txt
star_ray_pygame-0.0.11.dist-info/RECORD
