Metadata-Version: 2.1
Name: star_ray_pygame
Version: 0.0.11
Summary: An extension to the `star_ray` package that uses XML as a description language for the state of an environment.
Author-email: Benedict Wilkins <benrjw@gmail.com>
License: GNU GENERAL PUBLIC LICENSE
Project-URL: Repository, https://github.com/dicelab-rhul/star-ray-pygame
Requires-Python: >=3.10
License-File: LICENSE
Requires-Dist: star-ray>=0.0.8
Requires-Dist: star-ray-xml>=0.0.6
Requires-Dist: cairosvg>=1.26.1
Requires-Dist: pygame>=2.6.0
Requires-Dist: pywinctl>=0.4.0
Requires-Dist: numpy
